apeer_dev_kit/__init__.py
apeer_dev_kit/_core.py
apeer_dev_kit/_utility.py
apeer_dev_kit/adk.py
apeer_dev_kit-1.3.0.dist-info/licenses/LICENSE
apeer_dev_kit-1.3.0.dist-info/METADATA
apeer_dev_kit-1.3.0.dist-info/WHEEL
apeer_dev_kit-1.3.0.dist-info/top_level.txt
apeer_dev_kit-1.3.0.dist-info/RECORD
