Metadata-Version: 2.4
Name: apeer-dev-kit
Version: 1.3.0
Summary: Development kit for creating modules on apeer
Home-page: https://github.com/apeer-micro/apeer-python-sdk
Author: apeer-micro
Classifier: Programming Language :: Python :: 3
Classifier: Programming Language :: Python :: 3.8
Classifier: Programming Language :: Python :: 3.9
Classifier: Programming Language :: Python :: 3.10
Classifier: Programming Language :: Python :: 3.11
Classifier: Programming Language :: Python :: 3.12
Classifier: Programming Language :: Python :: 3.13
Classifier: License :: OSI Approved :: MIT License
Classifier: Operating System :: OS Independent
Requires-Python: >=3.8, <3.14
License-File: LICENSE
Dynamic: author
Dynamic: classifier
Dynamic: description
Dynamic: home-page
Dynamic: license-file
Dynamic: requires-python
Dynamic: summary
